django_model_docs/__init__.py
django_model_docs/admin.py
django_model_docs/apps.py
django_model_docs/models.py
django_model_docs/views.py
django_model_docs/management/__init__.py
django_model_docs/management/commands/__init__.py
django_model_docs/management/commands/generate-model-docs.py
django_model_docs/migrations/__init__.py
django_model_docs/serializers/__init__.py
django_model_docs/serializers/app_serializer.py
django_model_docs/serializers/model_serializer.py
django_model_docs/serializers/utils.py
django_model_docs/serializers/column_serializers/__init__.py
django_model_docs/serializers/column_serializers/column_serializer.py
django_model_docs/serializers/column_serializers/data_type.py
django_model_docs/serializers/column_serializers/default.py
django_model_docs/serializers/column_serializers/description.py
django_model_docs/serializers/column_serializers/field_name.py
django_model_docs/serializers/column_serializers/nullable.py
django_model_docs/tests/__init__.py
django_model_docs/tests/tests.py
django_model_docs/tests/serializers/__init__.py
django_model_docs/tests/serializers/test_app_serializer.py
django_model_docs/tests/serializers/test_data_type_serializer.py
django_model_docs/tests/serializers/test_description_serializer.py
django_model_docs/tests/serializers/test_model_serializer.py
django_model_docs/tests/serializers/test_nullable_serializer.py
django_model_docs-0.0.0.dist-info/LICENSE.txt
django_model_docs-0.0.0.dist-info/METADATA
django_model_docs-0.0.0.dist-info/WHEEL
django_model_docs-0.0.0.dist-info/top_level.txt
django_model_docs-0.0.0.dist-info/RECORD
