Metadata-Version: 2.1
Name: django-model-docs
Version: 0.0.0
Summary: Docs generator for Django models
Author: Jake Kara
Maintainer: Jake Kara
License: 
Project-URL: Homepage, https://github.com/jakekara/django-model-docs/
Project-URL: Bug Reports, https://github.com/jakekara/django-model-docs/issues
Project-URL: Source, https://github.com/jakekara/django-model-docs/
Keywords: sample,setuptools,development
Classifier: Development Status :: 3 - Alpha
Classifier: Intended Audience :: Developers
Classifier: Topic :: Documentation
Classifier: License :: OSI Approved :: MIT License
Classifier: Programming Language :: Python :: 3
Classifier: Programming Language :: Python :: 3.9
Classifier: Programming Language :: Python :: 3.10
Classifier: Programming Language :: Python :: 3.11
Classifier: Programming Language :: Python :: 3 :: Only
Requires-Python: >=3.9
License-File: LICENSE.txt
Requires-Dist: py-markdown-table <1
Provides-Extra: dev
Provides-Extra: test
Requires-Dist: tox >=4 ; extra == 'test'
